turbine_lib/__init__.py
turbine_lib/binarydata.py
turbine_lib/database.py
turbine_lib/datexportapi.py
turbine_lib/datfile.py
turbine_lib/ddssubfile.py
turbine_lib/font_convert.py
turbine_lib/fontsubfile.py
turbine_lib/subfile.py
turbine_lib/subfiledata.py
turbine_lib/textsubfile.py
turbine_lib/textutils.py
turbine_lib/utils.py
turbine_lib/libs/datexport.dll
turbine_lib/libs/msvcp71.dll
turbine_lib/libs/msvcp90.dll
turbine_lib/libs/msvcr71.dll
turbine_lib/libs/zlib1T.dll
turbine_lib-0.1.5.dist-info/METADATA
turbine_lib-0.1.5.dist-info/WHEEL
turbine_lib-0.1.5.dist-info/top_level.txt
turbine_lib-0.1.5.dist-info/RECORD
