Metadata-Version: 2.4
Name: turbine_lib
Version: 0.1.5
Summary: 仅支持Windows 32位Python的库
Classifier: Programming Language :: Python :: 3
Classifier: License :: OSI Approved :: MIT License
Classifier: Operating System :: Microsoft :: Windows
Classifier: Programming Language :: Python :: Implementation :: CPython
Classifier: Topic :: Software Development :: Libraries
Requires-Python: <3.13,>=3.7
